place_cz_bot/__init__.py
place_cz_bot/__main__.py
place_cz_bot/bot.py
place_cz_bot/version.py
place_cz_bot-1.0.5.dist-info/LICENSE
place_cz_bot-1.0.5.dist-info/METADATA
place_cz_bot-1.0.5.dist-info/WHEEL
place_cz_bot-1.0.5.dist-info/entry_points.txt
place_cz_bot-1.0.5.dist-info/top_level.txt
place_cz_bot-1.0.5.dist-info/RECORD
