Metadata-Version: 2.1
Name: place-cz-bot
Version: 1.0.5
Summary: PlaceNL: bot to automatically place pixels on /r/place 2022
Home-page: https://github.com/PlaceCZ/PythonBot
Author: Lucas van Dijk, fuho
Author-email: info@lucasvandijk.nl
License: MIT
Project-URL: Documentation, https://github.com/PlaceCZ/PythonBot/blob/main/README.md
Project-URL: Source, https://github.com/PlaceCZ/PythonBot
Project-URL: Tracker, https://github.com/PlaceCZ/PythonBot/issues
Keywords: bot
Platform: UNKNOWN
Classifier: Development Status :: 4 - Beta
Classifier: Programming Language :: Python
Classifier: Programming Language :: Python :: 3 :: Only
Classifier: Programming Language :: Python :: 3.8
Classifier: Programming Language :: Python :: 3.9
Classifier: Programming Language :: Python :: 3.10
Classifier: License :: OSI Approved :: MIT License
Classifier: Natural Language :: English
Classifier: Intended Audience :: Developers
Classifier: Intended Audience :: Information Technology
Classifier: Operating System :: Unix
Classifier: Operating System :: POSIX :: BSD
Classifier: Operating System :: POSIX :: Linux
Classifier: Operating System :: MacOS :: MacOS X
Classifier: Topic :: Internet
Classifier: Topic :: Internet :: WWW/HTTP
Classifier: Topic :: Internet :: WWW/HTTP :: HTTP Servers
Classifier: Topic :: Software Development :: Libraries
Classifier: Topic :: Software Development :: Libraries :: Python Modules
Requires-Python: >=3.8
License-File: LICENSE
Requires-Dist: aiohttp
Requires-Dist: numpy
Requires-Dist: matplotlib
Requires-Dist: rich
Provides-Extra: test
Requires-Dist: pytest (>=7.0.1) ; extra == 'test'
